{
  "titulo": "De repente el último verano",
  "slug": "de-repente-el-ultimo-verano",
  "imdb_id": "tt0053318",
  "year": "1959",
  "director": "Joseph L. Mankiewicz",
  "plot": "En la Nueva Orleans de 1937, una rica viuda, la señora Venable, ofrece al doctor Cukrowicz los fondos para crear un hospital a condición de que practique una lobotomía a su sobrina Catherine. La señora Venable se encuentra perturbada por la reciente muerte en Europa de su hijo Sebastian, con quien solía viajar todos los veranos, salvo el último, en el que Sebastian prefirió llevar como acompañante a su prima Catherine.",
  "poster": "https://image.tmdb.org/t/p/w500/tFD6PQENC63tKrYb1Hb8QEn463Z.jpg",
  "genre": "Suspense, Drama, Misterio",
  "imdb_rating": null,
  "runtime": "114 min",
  "traida_por": [
    "Beiger"
  ],
  "findes": [
    14
  ],
  "tmdb_id": 14698,
  "titulo_es": "De repente, el último verano",
  "titulo_original": "Suddenly, Last Summer",
  "tmdb_rating": 7.3
}