{
  "titulo": "Fingers",
  "slug": "fingers",
  "imdb_id": "tt0077549",
  "year": "1978",
  "director": "James Toback",
  "plot": "Thriller con un entonces apenas conocido Harvey Keitel que supuso el debut de James Toback. Jimmy Fingers es un joven que se debate entre la lealtad a su padre, con conexiones a la mafia italiana, o a su madre, una judía concertista de piano mentalmente perturbada.",
  "poster": "https://image.tmdb.org/t/p/w500/eAOmuZ8QzXvsAaWEATKC0SuPd5K.jpg",
  "genre": "Drama, Acción, Suspense, Crimen",
  "imdb_rating": null,
  "runtime": "90 min",
  "traida_por": [
    "Romulo"
  ],
  "findes": [
    21
  ],
  "tmdb_id": 63435,
  "titulo_es": "Melodía para un asesinato",
  "titulo_original": "Fingers",
  "tmdb_rating": 6.3
}