{
  "titulo": "Grand Theft Hamlet",
  "slug": "grand-theft-hamlet",
  "imdb_id": "tt28244549",
  "year": "2024",
  "director": "Sam Crane, Pinny Grylls",
  "plot": "Dos amigos desempleados tienen una nueva idea: quieren representar 'Hamlet' de Shakespeare en Grand Theft Auto. Pero incluso en un mundo virtual, la realidad se entromete en una película salvaje y alucinante filmada íntegramente dentro del videojuego ultraviolento.",
  "poster": "https://image.tmdb.org/t/p/w500/61pws82KZEssg883HG3kwN16cRw.jpg",
  "genre": "Animación, Documental",
  "imdb_rating": null,
  "runtime": "91 min",
  "traida_por": [
    "Sherlock"
  ],
  "findes": [
    27
  ],
  "tmdb_id": 1234397,
  "titulo_es": "Grand Theft Hamlet",
  "titulo_original": "Grand Theft Hamlet",
  "tmdb_rating": 6.6
}