{
  "titulo": "La gata negra",
  "slug": "la-gata-negra",
  "imdb_id": "tt0056671",
  "year": "1962",
  "director": "Edward Dmytryk",
  "plot": "Un hombre busca a su antigua amada y la encuentra en un burdel convertida en amante de una madame lesbiana.",
  "poster": "https://image.tmdb.org/t/p/w500/dwFIuQvO2Juc1JuOSKUbbox6oj9.jpg",
  "genre": "Drama",
  "imdb_rating": null,
  "runtime": "114 min",
  "traida_por": [
    "Hypnos"
  ],
  "findes": [
    26
  ],
  "tmdb_id": 60792,
  "titulo_es": "La gata negra",
  "titulo_original": "Walk on the Wild Side",
  "tmdb_rating": 6.5
}