{
  "titulo": "Reencarnación",
  "slug": "reencarnacion",
  "imdb_id": null,
  "year": "2018",
  "director": "Martín Piroyansky",
  "plot": "En una consulta médica, un hombre descubre ser la reencarnación de Adolf Hitler",
  "poster": "https://image.tmdb.org/t/p/w500/jS6nJIQqbmNOOZJYcm9Ij57L3ki.jpg",
  "genre": "Comedia",
  "imdb_rating": null,
  "runtime": "3 min",
  "traida_por": [
    "Romulo"
  ],
  "findes": [
    3
  ],
  "tmdb_id": 1156835,
  "titulo_es": "Reencarnación",
  "titulo_original": "Reencarnación",
  "tmdb_rating": 4.0
}