{
  "titulo": "Shine",
  "slug": "shine",
  "imdb_id": "tt0117631",
  "year": "1996",
  "director": "Scott Hicks",
  "plot": "Basada en hechos reales, narra la historia de David Helfgott, un brillante y virtuoso pianista australiano cuya insoportable presión paterna le traumatizó hasta el punto de alcanzar estados de demencia y sufrir internamiento en un asilo.",
  "poster": "https://image.tmdb.org/t/p/w500/cbmThowj2XAW7lKlMAXmnhZvjGI.jpg",
  "genre": "Drama",
  "imdb_rating": null,
  "runtime": "105 min",
  "traida_por": [
    "Munny"
  ],
  "findes": [
    3
  ],
  "tmdb_id": 7863,
  "titulo_es": "Shine. El resplandor de un genio",
  "titulo_original": "Shine",
  "tmdb_rating": 7.4
}