{
  "titulo": "Te querré siempre",
  "slug": "te-querre-siempre",
  "imdb_id": "tt0046511",
  "year": "1954",
  "director": "Roberto Rossellini",
  "plot": "Un matrimonio inglés viaja a Italia para vender una villa que ha heredado cerca de Nápoles. Al alejarse del ambiente londinense y encontrarse en un paisaje y en un mundo ajenos, la pareja experimenta sentimientos olvidados, como los celos y el resentimiento.",
  "poster": "https://image.tmdb.org/t/p/w500/eVoEcFjS4AiLtKj4PIMKdYbLN6x.jpg",
  "genre": "Drama, Romance",
  "imdb_rating": null,
  "runtime": "110 min",
  "traida_por": [
    "Hypnos"
  ],
  "findes": [
    4
  ],
  "tmdb_id": 2748,
  "titulo_es": "Te querré siempre",
  "titulo_original": "Viaggio in Italia",
  "tmdb_rating": 7.3
}